sect/__init__.py
sect/decomposition.py
sect/triangulation.py
sect/core/__init__.py
sect/core/hints.py
sect/core/utils.py
sect/core/delaunay/__init__.py
sect/core/delaunay/event.py
sect/core/delaunay/events_queue.py
sect/core/delaunay/hints.py
sect/core/delaunay/quad_edge.py
sect/core/delaunay/sweep_line.py
sect/core/delaunay/triangulation.py
sect/core/delaunay/utils.py
sect/core/trapezoidal/__init__.py
sect/core/trapezoidal/edge.py
sect/core/trapezoidal/graph.py
sect/core/trapezoidal/hints.py
sect/core/trapezoidal/leaf.py
sect/core/trapezoidal/node.py
sect/core/trapezoidal/trapezoid.py
sect/core/trapezoidal/x_node.py
sect/core/trapezoidal/y_node.py
sect-7.1.0.dist-info/LICENSE
sect-7.1.0.dist-info/METADATA
sect-7.1.0.dist-info/WHEEL
sect-7.1.0.dist-info/top_level.txt
sect-7.1.0.dist-info/RECORD
